{
  "version": "1",
  "cognitoConfig": {
    "identityPoolName": "docnow135a21e5_identitypool_135a21e5",
    "allowUnauthenticatedIdentities": true,
    "resourceNameTruncated": "docnow135a21e5",
    "userPoolName": "docnow135a21e5_userpool_135a21e5",
    "autoVerifiedAttributes": [
      "phone_number"
    ],
    "mfaConfiguration": "OFF",
    "mfaTypes": [
      "SMS Text Message"
    ],
    "smsAuthenticationMessage": "Your authentication code is {####}",
    "smsVerificationMessage": "Your DocNow Verification Code is {####}",
    "emailVerificationSubject": "Your verification code",
    "emailVerificationMessage": "Your verification code is {####}",
    "defaultPasswordPolicy": true,
    "passwordPolicyMinLength": "8",
    "passwordPolicyCharacters": [
      "Requires Lowercase",
      "Requires Uppercase",
      "Requires Numbers",
      "Requires Symbols"
    ],
    "requiredAttributes": [
      "email",
      "name",
      "phone_number"
    ],
    "aliasAttributes": [],
    "userpoolClientGenerateSecret": false,
    "userpoolClientRefreshTokenValidity": 30,
    "userpoolClientWriteAttributes": [
      "email"
    ],
    "userpoolClientReadAttributes": [
      "email"
    ],
    "userpoolClientLambdaRole": "docnow135a21e5_userpoolclient_lambda_role",
    "userpoolClientSetAttributes": false,
    "sharedId": "135a21e5",
    "resourceName": "docnow135a21e5135a21e5",
    "authSelections": "identityPoolAndUserPool",
    "useDefault": "manual",
    "thirdPartyAuth": false,
    "usernameAttributes": [
      "phone_number"
    ],
    "userPoolGroups": true,
    "adminQueries": true,
    "triggers": {},
    "hostedUI": false,
    "userPoolGroupList": [
      "admin"
    ],
    "adminQueryGroup": "admin",
    "serviceName": "Cognito",
    "usernameCaseSensitive": false,
    "useEnabledMfas": true
  }
}